LICENSE
README.md
setup.py
gitlab_submodule/__init__.py
gitlab_submodule/__version__.py
gitlab_submodule/gitlab_submodule.py
gitlab_submodule/objects.py
gitlab_submodule/project_manager_utils.py
gitlab_submodule/read_gitmodules.py
gitlab_submodule/string_utils.py
gitlab_submodule/submodule_commit.py
gitlab_submodule/submodule_to_project.py
python_gitlab_submodule.egg-info/PKG-INFO
python_gitlab_submodule.egg-info/SOURCES.txt
python_gitlab_submodule.egg-info/dependency_links.txt
python_gitlab_submodule.egg-info/requires.txt
python_gitlab_submodule.egg-info/top_level.txt
tests/test_gitlab_submodule.py
tests/test_gitmodules_to_project.py
tests/test_objects.py
tests/test_project_manager_utils.py
tests/test_read_gitmodules.py
tests/test_string_utils.py
tests/test_submodule_commit.py
tests/test_submodule_to_project.py