Metadata-Version: 2.1
Name: python-gitlab-submodule
Version: 0.4.0
Summary: python-gitlab-submodule : List project submodules and get the commits they point to with python-gitlab.
Home-page: https://github.com/ValentinFrancois/python-gitlab-submodule
Author: Valentin François
Maintainer: Valentin François
License: Apache License 2.0
Platform: any
Requires-Python: >=3.8.0
License-File: LICENSE
Requires-Dist: python-gitlab>=3.0.0
Requires-Dist: giturlparse>=0.10.0
